{"metadata": {"dataVersion": "2", "matchId": "EUN1_3298813385", "participants": ["WH35mbb2g5naD0XH3uAppg01kxZ_4oKomYP-Uk8BninHE_QFITgHywS7vL_CW4MT4sXvhDRSaMxfOQ", "3n0enWwkpuX1ku2XUfHoDyO6ov3koQzQEcZO9dfKibmAvWGwgoqXIDaqJHidP49f3LlexQ0JpMUBTw", "DjjA6Dq1BFAHFjNAi0Z6d9Ymuvkx3xAKuNnaoe20mU_pUQ4vuMH0UENx2c6UCwTOIjVhYrN6E1ryDw", "5zPeohIhsnYKveqPpjMCnUM0QDnfmrPxMq9oVdqbt1rqLlaIf25m3Q78FI9ENuSq7okhEdh-8cODJA", "KVrHIDsUfkjhE0TAROUdnTFqBgacRUT4VCaTLXZny2d2T3ZrplCH9OHACSUTcu-pDuqP8tl2MCHqAQ", "1Pavvm2ONGKUD_YKXMvTUQyEVHtNxxGhtBSu7-GFyLh95UG0ORPlpSpZ9oZeUm1Kye0QjH_soaeLow", "nwiIR1_T4TBsUucBfIUPWyGWwKXOpWywFHNbaz4V8THiv8o2XvXeWT-csMLWp-CZXJGIUDRDUVcHsw", "ajcnX3-CQTwe5VDcY6U5DyBSksUQEMj7g65xcDMlwg8z2DgUc0JEu-_mmfu76ZDn8il9lXoK7OhEwA", "jFlqFX1_gINeXgK5BSxlJFNm-naSe0GvSs9uKZ_VI-4SziZX-bsatn_GHwxaohopdq4kgW6mwLcvKQ", "yGux9w-P3Ue5zCobrjqusGcAbwxmtD5CyC8bL5rL1H5dTnN4VEbhQazFPg2PZO77vZ2XzC26WmVdkg"]}, "info": {"gameCreation": 1674306184358, "gameDuration": 1619, "gameEndTimestamp": 1674307842465, "gameId": 3298813385, "gameMode": "CLASSIC", "gameName": "teambuilder-match-3298813385", "gameStartTimestamp": 1674306222945, "gameType": "MATCHED_GAME", "gameVersion": "13.1.489.3737", "mapId": 11, "participants": [{"allInPings": 0, "assistMePings": 0, "assists": 6, "baitPings": 0, "baronKills": 0, "basicPings": 0, "bountyLevel": 2, "challenges": {"12AssistStreakCount": 0, "abilityUses": 189, "acesBefore15Minutes": 0, "alliedJungleMonsterKills": 0, "baronBuffGoldAdvantageOverThreshold": 1, "baronTakedowns": 0, "blastConeOppositeOpponentCount": 0, "bountyGold": 0, "buffsStolen": 0, "completeSupportQuestInTime": 0, "controlWardsPlaced": 1, "damagePerMinute": 325.4503840601679, "damageTakenOnTeamPercentage": 0.16838205364940328, "dancedWithRiftHerald": 0, "deathsByEnemyChamps": 1, "dodgeSkillShotsSmallWindow": 0, "doubleAces": 0, "dragonTakedowns": 0, "earliestBaron": 1468.9055563454224, "earlyLaningPhaseGoldExpAdvantage": 0, "effectiveHealAndShielding": 0, "elderDragonKillsWithOpposingSoul": 0, "elderDragonMultikills": 0, "enemyChampionImmobilizations": 36, "enemyJungleMonsterKills": 2.5, "epicMonsterKillsNearEnemyJungler": 0, "epicMonsterKillsWithin30SecondsOfSpawn": 0, "epicMonsterSteals": 0, "epicMonsterStolenWithoutSmite": 0, "firstTurretKilledTime": 927.1206063237158, "flawlessAces": 1, "fullTeamTakedown": 1, "gameLength": 1619.6166577078031, "getTakedownsInAllLanesEarlyJungleAsLaner": 0, "goldPerMinute": 438.960642548703, "hadOpenNexus": 0, "immobilizeAndKillWithAlly": 4, "initialBuffCount": 0, "initialCrabCount": 0, "jungleCsBefore10Minutes": 0, "junglerTakedownsNearDamagedEpicMonster": 0, "kTurretsDestroyedBeforePlatesFall": 0, "kda": 8, "killAfterHiddenWithAlly": 0, "killParticipation": 0.25806451612903225, "killedChampTookFullTeamDamageSurvived": 0, "killsNearEnemyTurret": 0, "killsOnOtherLanesEarlyJungleAsLaner": 0, "killsOnRecentlyHealedByAramPack": 0, "killsUnderOwnTurret": 2, "killsWithHelpFromEpicMonster": 0, "knockEnemyIntoTeamAndKill": 0, "landSkillShotsEarlyGame": 5, "laneMinionsFirst10Minutes": 68, "laningPhaseGoldExpAdvantage": 0, "legendaryCount": 0, "lostAnInhibitor": 0, "maxCsAdvantageOnLaneOpponent": 18, "maxKillDeficit": 3, "maxLevelLeadLaneOpponent": 3, "moreEnemyJungleThanOpponent": 0, "multiKillOneSpell": 0, "multiTurretRiftHeraldCount": 0, "multikills": 0, "multikillsAfterAggressiveFlash": 0, "mythicItemUsed": 3084, "outerTurretExecutesBefore10Minutes": 0, "outnumberedKills": 1, "outnumberedNexusKill": 0, "perfectDragonSoulsTaken": 0, "perfectGame": 0, "pickKillWithAlly": 6, "playedChampSelectPosition": 1, "poroExplosions": 0, "quickCleanse": 0, "quickFirstTurret": 0, "quickSoloKills": 0, "riftHeraldTakedowns": 0, "saveAllyFromDeath": 0, "scuttleCrabKills": 0, "shortestTimeToAceFromFirstTakedown": 23.698614962239844, "skillshotsDodged": 4, "skillshotsHit": 18, "snowballsHit": 0, "soloBaronKills": 0, "soloKills": 2, "soloTurretsLategame": 2, "stealthWardsPlaced": 8, "survivedSingleDigitHpCount": 0, "survivedThreeImmobilizesInFight": 0, "takedownOnFirstTurret": 0, "takedowns": 8, "takedownsAfterGainingLevelAdvantage": 0, "takedownsBeforeJungleMinionSpawn": 0, "takedownsFirstXMinutes": 3, "takedownsInAlcove": 0, "takedownsInEnemyFountain": 0, "teamBaronKills": 1, "teamDamagePercentage": 0.10953351946154925, "teamElderDragonKills": 0, "teamRiftHeraldKills": 2, "threeWardsOneSweeperCount": 0, "tookLargeDamageSurvived": 0, "turretPlatesTaken": 2, "turretTakedowns": 4, "turretsTakenWithRiftHerald": 5, "twentyMinionsIn3SecondsCount": 10, "unseenRecalls": 0, "visionScoreAdvantageLaneOpponent": -0.10358679294586182, "visionScorePerMinute": 0.4732529148119361, "wardTakedowns": 0, "wardTakedownsBefore20M": 0, "wardsGuarded": 0}, "champExperience": 16797, "champLevel": 17, "championId": 14, "championName": "Sion", "championTransform": 0, "commandPings": 2, "consumablesPurchased": 2, "damageDealtToBuildings": 7759, "damageDealtToObjectives": 9837, "damageDealtToTurrets": 7759, "damageSelfMitigated": 33267, "dangerPings": 0, "deaths": 1, "detectorWardsPlaced": 1, "doubleKills": 0, "dragonKills": 0, "eligibleForProgression": true, "enemyMissingPings": 3, "enemyVisionPings": 0, "firstBloodAssist": false, "firstBloodKill": false, "firstTowerAssist": false, "firstTowerKill": false, "gameEndedInEarlySurrender": false, "gameEndedInSurrender": false, "getBackPings": 2, "goldEarned": 11849, "goldSpent": 11425, "holdPings": 0, "individualPosition": "TOP", "inhibitorKills": 0, "inhibitorTakedowns": 0, "inhibitorsLost": 0, "item0": 4401, "item1": 3084, "item2": 3068, "item3": 3076, "item4": 3111, "item5": 1054, "item6": 3340, "itemsPurchased": 18, "killingSprees": 1, "kills": 2, "lane": "TOP", "largestCriticalStrike": 0, "largestKillingSpree": 2, "largestMultiKill": 1, "longestTimeSpentLiving": 635, "magicDamageDealt": 41270, "magicDamageDealtToChampions": 3234, "magicDamageTaken": 12135, "needVisionPings": 0, "neutralMinionsKilled": 4, "nexusKills": 0, "nexusLost": 0, "nexusTakedowns": 0, "objectivesStolen": 0, "objectivesStolenAssists": 0, "onMyWayPings": 5, "participantId": 1, "pentaKills": 0, "perks": {"statPerks": {"defense": 5002, "flex": 5008, "offense": 5005}, "styles": [{"description": "primaryStyle", "selections": [{"perk": 8437, "var1": 578, "var2": 462, "var3": 0}, {"perk": 8446, "var1": 5269, "var2": 0, "var3": 0}, {"perk": 8429, "var1": 55, "var2": 14, "var3": 13}, {"perk": 8451, "var1": 307, "var2": 0, "var3": 0}], "style": 8400}, {"description": "subStyle", "selections": [{"perk": 9105, "var1": 19, "var2": 50, "var3": 0}, {"perk": 9111, "var1": 460, "var2": 160, "var3": 0}], "style": 8000}]}, "physicalDamageDealt": 104126, "physicalDamageDealtToChampions": 5549, "physicalDamageTaken": 7737, "profileIcon": 5212, "pushPings": 0, "puuid": "WH35mbb2g5naD0XH3uAppg01kxZ_4oKomYP-Uk8BninHE_QFITgHywS7vL_CW4MT4sXvhDRSaMxfOQ", "quadraKills": 0, "riotIdName": "", "riotIdTagline": "", "role": "SOLO", "sightWardsBoughtInGame": 0, "spell1Casts": 73, "spell2Casts": 57, "spell3Casts": 53, "spell4Casts": 6, "summoner1Casts": 2, "summoner1Id": 4, "summoner2Casts": 3, "summoner2Id": 12, "summonerId": "SoGjkcgV3PxDPc0jiVKxHTN4cOCbtHGdXMCF14Xwdj8TKhw", "summonerLevel": 172, "summonerName": "Lines99", "teamEarlySurrendered": false, "teamId": 100, "teamPosition": "TOP", "timeCCingOthers": 31, "timePlayed": 1619, "totalDamageDealt": 147037, "totalDamageDealtToChampions": 8785, "totalDamageShieldedOnTeammates": 0, "totalDamageTaken": 20508, "totalHeal": 5438, "totalHealsOnTeammates": 0, "totalMinionsKilled": 208, "totalTimeCCDealt": 743, "totalTimeSpentDead": 27, "totalUnitsHealed": 1, "tripleKills": 0, "trueDamageDealt": 1641, "trueDamageDealtToChampions": 1, "trueDamageTaken": 635, "turretKills": 2, "turretTakedowns": 4, "turretsLost": 5, "unrealKills": 0, "visionClearedPings": 0, "visionScore": 12, "visionWardsBoughtInGame": 1, "wardsKilled": 0, "wardsPlaced": 9, "win": true}, {"allInPings": 0, "assistMePings": 1, "assists": 5, "baitPings": 1, "baronKills": 1, "basicPings": 0, "bountyLevel": 4, "challenges": {"12AssistStreakCount": 0, "abilityUses": 390, "acesBefore15Minutes": 0, "alliedJungleMonsterKills": 100.00000017881393, "baronBuffGoldAdvantageOverThreshold": 1, "baronTakedowns": 1, "blastConeOppositeOpponentCount": 0, "bountyGold": 450, "buffsStolen": 1, "completeSupportQuestInTime": 0, "controlWardTimeCoverageInRiverOrEnemyHalf": 0.11270183438617265, "controlWardsPlaced": 3, "damagePerMinute": 896.9626108893661, "damageTakenOnTeamPercentage": 0.3184152435017327, "dancedWithRiftHerald": 0, "deathsByEnemyChamps": 7, "dodgeSkillShotsSmallWindow": 2, "doubleAces": 0, "dragonTakedowns": 3, "earliestBaron": 1468.9055563454224, "earliestDragonTakedown": 456.3164047561301, "earlyLaningPhaseGoldExpAdvantage": 0, "effectiveHealAndShielding": 0, "elderDragonKillsWithOpposingSoul": 0, "elderDragonMultikills": 0, "enemyChampionImmobilizations": 34, "enemyJungleMonsterKills": 4, "epicMonsterKillsNearEnemyJungler": 1, "epicMonsterKillsWithin30SecondsOfSpawn": 1, "epicMonsterSteals": 1, "epicMonsterStolenWithoutSmite": 1, "firstTurretKilledTime": 927.1206063237158, "flawlessAces": 1, "fullTeamTakedown": 1, "gameLength": 1619.6166577078031, "goldPerMinute": 485.3936858931594, "hadOpenNexus": 0, "highestChampionDamage": 1, "immobilizeAndKillWithAlly": 9, "initialBuffCount": 3, "initialCrabCount": 1, "jungleCsBefore10Minutes": 48.000000059604645, "junglerKillsEarlyJungle": 1, "junglerTakedownsNearDamagedEpicMonster": 1, "kTurretsDestroyedBeforePlatesFall": 0, "kda": 2.2857142857142856, "killAfterHiddenWithAlly": 1, "killParticipation": 0.5161290322580645, "killedChampTookFullTeamDamageSurvived": 0, "killingSprees": 1, "killsNearEnemyTurret": 3, "killsOnLanersEarlyJungleAsJungler": 2, "killsOnRecentlyHealedByAramPack": 0, "killsUnderOwnTurret": 1, "killsWithHelpFromEpicMonster": 0, "knockEnemyIntoTeamAndKill": 0, "landSkillShotsEarlyGame": 3, "laneMinionsFirst10Minutes": 1, "laningPhaseGoldExpAdvantage": 0, "legendaryCount": 0, "lostAnInhibitor": 0, "maxCsAdvantageOnLaneOpponent": 4, "maxKillDeficit": 3, "maxLevelLeadLaneOpponent": 1, "moreEnemyJungleThanOpponent": -41.00000008940697, "multiKillOneSpell": 0, "multiTurretRiftHeraldCount": 0, "multikills": 1, "multikillsAfterAggressiveFlash": 0, "mythicItemUsed": 4636, "outerTurretExecutesBefore10Minutes": 0, "outnumberedKills": 1, "outnumberedNexusKill": 0, "perfectDragonSoulsTaken": 0, "perfectGame": 0, "pickKillWithAlly": 11, "playedChampSelectPosition": 1, "poroExplosions": 0, "quickCleanse": 0, "quickFirstTurret": 0, "quickSoloKills": 1, "riftHeraldTakedowns": 2, "saveAllyFromDeath": 0, "scuttleCrabKills": 1, "shortestTimeToAceFromFirstTakedown": 23.698614962239844, "skillshotsDodged": 11, "skillshotsHit": 20, "snowballsHit": 0, "soloBaronKills": 0, "soloKills": 4, "stealthWardsPlaced": 2, "survivedSingleDigitHpCount": 0, "survivedThreeImmobilizesInFight": 0, "takedownOnFirstTurret": 0, "takedowns": 16, "takedownsAfterGainingLevelAdvantage": 1, "takedownsBeforeJungleMinionSpawn": 0, "takedownsFirstXMinutes": 5, "takedownsInAlcove": 0, "takedownsInEnemyFountain": 0, "teamBaronKills": 1, "teamDamagePercentage": 0.3018815660022968, "teamElderDragonKills": 0, "teamRiftHeraldKills": 2, "threeWardsOneSweeperCount": 0, "tookLargeDamageSurvived": 0, "turretPlatesTaken": 1, "turretTakedowns": 3, "turretsTakenWithRiftHerald": 5, "twentyMinionsIn3SecondsCount": 0, "unseenRecalls": 0, "visionScoreAdvantageLaneOpponent": -0.3059998154640198, "visionScorePerMinute": 0.48848609782734626, "wardTakedowns": 1, "wardTakedownsBefore20M": 1, "wardsGuarded": 0}, "champExperience": 14379, "champLevel": 15, "championId": 517, "championName": "Sylas", "championTransform": 0, "commandPings": 8, "consumablesPurchased": 5, "damageDealtToBuildings": 2356, "damageDealtToObjectives": 22649, "damageDealtToTurrets": 2356, "damageSelfMitigated": 31373, "dangerPings": 0, "deaths": 7, "detectorWardsPlaced": 3, "doubleKills": 1, "dragonKills": 2, "eligibleForProgression": true, "enemyMissingPings": 0, "enemyVisionPings": 0, "firstBloodAssist": false, "firstBloodKill": true, "firstTowerAssist": false, "firstTowerKill": false, "gameEndedInEarlySurrender": false, "gameEndedInSurrender": false, "getBackPings": 1, "goldEarned": 13102, "goldSpent": 11585, "holdPings": 0, "individualPosition": "JUNGLE", "inhibitorKills": 1, "inhibitorTakedowns": 2, "inhibitorsLost": 0, "item0": 4645, "item1": 3157, "item2": 2055, "item3": 3020, "item4": 4636, "item5": 1052, "item6": 3364, "itemsPurchased": 24, "killingSprees": 3, "kills": 11, "lane": "JUNGLE", "largestCriticalStrike": 0, "largestKillingSpree": 4, "largestMultiKill": 2, "longestTimeSpentLiving": 276, "magicDamageDealt": 132164, "magicDamageDealtToChampions": 23201, "magicDamageTaken": 14509, "needVisionPings": 0, "neutralMinionsKilled": 130, "nexusKills": 0, "nexusLost": 0, "nexusTakedowns": 1, "objectivesStolen": 1, "objectivesStolenAssists": 0, "onMyWayPings": 12, "participantId": 2, "pentaKills": 0, "perks": {"statPerks": {"defense": 5003, "flex": 5008, "offense": 5008}, "styles": [{"description": "primaryStyle", "selections": [{"perk": 8128, "var1": 1585, "var2": 18, "var3": 0}, {"perk": 8143, "var1": 1085, "var2": 0, "var3": 0}, {"perk": 8138, "var1": 30, "var2": 0, "var3": 0}, {"perk": 8135, "var1": 550, "var2": 5, "var3": 0}], "style": 8100}, {"description": "subStyle", "selections": [{"perk": 8347, "var1": 0, "var2": 0, "var3": 0}, {"perk": 8304, "var1": 9, "var2": 0, "var3": 0}], "style": 8300}]}, "physicalDamageDealt": 10339, "physicalDamageDealtToChampions": 220, "physicalDamageTaken": 22515, "profileIcon": 938, "pushPings": 0, "puuid": "3n0enWwkpuX1ku2XUfHoDyO6ov3koQzQEcZO9dfKibmAvWGwgoqXIDaqJHidP49f3LlexQ0JpMUBTw", "quadraKills": 0, "riotIdName": "", "riotIdTagline": "", "role": "NONE", "sightWardsBoughtInGame": 0, "spell1Casts": 85, "spell2Casts": 95, "spell3Casts": 193, "spell4Casts": 17, "summoner1Casts": 16, "summoner1Id": 11, "summoner2Casts": 4, "summoner2Id": 4, "summonerId": "w3wFA8RvUSR3GPAI32rrCmrbz7jRSrVuiippKcKtAIpmdeQ", "summonerLevel": 501, "summonerName": "krollllllll1", "teamEarlySurrendered": false, "teamId": 100, "teamPosition": "JUNGLE", "timeCCingOthers": 22, "timePlayed": 1619, "totalDamageDealt": 187783, "totalDamageDealtToChampions": 24212, "totalDamageShieldedOnTeammates": 0, "totalDamageTaken": 38783, "totalHeal": 8035, "totalHealsOnTeammates": 0, "totalMinionsKilled": 26, "totalTimeCCDealt": 451, "totalTimeSpentDead": 183, "totalUnitsHealed": 1, "tripleKills": 0, "trueDamageDealt": 45280, "trueDamageDealtToChampions": 790, "trueDamageTaken": 1757, "turretKills": 3, "turretTakedowns": 3, "turretsLost": 5, "unrealKills": 0, "visionClearedPings": 0, "visionScore": 13, "visionWardsBoughtInGame": 4, "wardsKilled": 1, "wardsPlaced": 5, "win": true}, {"allInPings": 1, "assistMePings": 1, "assists": 7, "baitPings": 8, "baronKills": 0, "basicPings": 0, "bountyLevel": 5, "challenges": {"12AssistStreakCount": 0, "abilityUses": 639, "acesBefore15Minutes": 0, "alliedJungleMonsterKills": 8.000000029802322, "baronBuffGoldAdvantageOverThreshold": 1, "baronTakedowns": 1, "blastConeOppositeOpponentCount": 0, "bountyGold": 500, "buffsStolen": 0, "completeSupportQuestInTime": 0, "controlWardTimeCoverageInRiverOrEnemyHalf": 0.08999438283053021, "controlWardsPlaced": 2, "damagePerMinute": 700.2087322116804, "damageTakenOnTeamPercentage": 0.2663427861546678, "dancedWithRiftHerald": 0, "deathsByEnemyChamps": 9, "dodgeSkillShotsSmallWindow": 3, "doubleAces": 0, "dragonTakedowns": 0, "earliestBaron": 1468.9055563454224, "earlyLaningPhaseGoldExpAdvantage": 0, "effectiveHealAndShielding": 0, "elderDragonKillsWithOpposingSoul": 0, "elderDragonMultikills": 0, "enemyChampionImmobilizations": 15, "enemyJungleMonsterKills": 8.000000029802322, "epicMonsterKillsNearEnemyJungler": 0, "epicMonsterKillsWithin30SecondsOfSpawn": 0, "epicMonsterSteals": 0, "epicMonsterStolenWithoutSmite": 0, "firstTurretKilledTime": 927.1206063237158, "flawlessAces": 1, "fullTeamTakedown": 1, "gameLength": 1619.6166577078031, "getTakedownsInAllLanesEarlyJungleAsLaner": 0, "goldPerMinute": 428.1556769042294, "hadOpenNexus": 0, "immobilizeAndKillWithAlly": 7, "initialBuffCount": 0, "initialCrabCount": 0, "jungleCsBefore10Minutes": 0, "junglerTakedownsNearDamagedEpicMonster": 0, "kTurretsDestroyedBeforePlatesFall": 0, "kda": 1.3333333333333333, "killAfterHiddenWithAlly": 0, "killParticipation": 0.3870967741935484, "killedChampTookFullTeamDamageSurvived": 0, "killingSprees": 1, "killsNearEnemyTurret": 0, "killsOnOtherLanesEarlyJungleAsLaner": 0, "killsOnRecentlyHealedByAramPack": 0, "killsUnderOwnTurret": 0, "killsWithHelpFromEpicMonster": 0, "knockEnemyIntoTeamAndKill": 0, "landSkillShotsEarlyGame": 10, "laneMinionsFirst10Minutes": 64, "laningPhaseGoldExpAdvantage": 0, "legendaryCount": 0, "lostAnInhibitor": 0, "maxCsAdvantageOnLaneOpponent": 50.000000059604645, "maxKillDeficit": 3, "maxLevelLeadLaneOpponent": 1, "moreEnemyJungleThanOpponent": 0, "multiKillOneSpell": 0, "multiTurretRiftHeraldCount": 0, "multikills": 1, "multikillsAfterAggressiveFlash": 0, "mythicItemUsed": 6657, "outerTurretExecutesBefore10Minutes": 0, "outnumberedKills": 0, "outnumberedNexusKill": 0, "perfectDragonSoulsTaken": 0, "perfectGame": 0, "pickKillWithAlly": 11, "playedChampSelectPosition": 1, "poroExplosions": 0, "quickCleanse": 0, "quickFirstTurret": 0, "quickSoloKills": 0, "riftHeraldTakedowns": 0, "saveAllyFromDeath": 0, "scuttleCrabKills": 1, "skillshotsDodged": 19, "skillshotsHit": 58, "snowballsHit": 0, "soloBaronKills": 0, "soloKills": 0, "stealthWardsPlaced": 3, "survivedSingleDigitHpCount": 0, "survivedThreeImmobilizesInFight": 0, "takedownOnFirstTurret": 0, "takedowns": 12, "takedownsAfterGainingLevelAdvantage": 0, "takedownsBeforeJungleMinionSpawn": 0, "takedownsFirstXMinutes": 0, "takedownsInAlcove": 0, "takedownsInEnemyFountain": 0, "teamBaronKills": 1, "teamDamagePercentage": 0.23566211795490014, "teamElderDragonKills": 0, "teamRiftHeraldKills": 2, "threeWardsOneSweeperCount": 0, "tookLargeDamageSurvived": 0, "turretPlatesTaken": 0, "turretTakedowns": 3, "turretsTakenWithRiftHerald": 5, "twentyMinionsIn3SecondsCount": 9, "unseenRecalls": 0, "visionScoreAdvantageLaneOpponent": -0.3582417964935303, "visionScorePerMinute": 0.789202767082542, "wardTakedowns": 1, "wardTakedownsBefore20M": 0, "wardsGuarded": 0}, "champExperience": 14781, "champLevel": 16, "championId": 13, "championName": "Ryze", "championTransform": 0, "commandPings": 0, "consumablesPurchased": 4, "damageDealtToBuildings": 1494, "damageDealtToObjectives": 4360, "damageDealtToTurrets": 1494, "damageSelfMitigated": 18680, "dangerPings": 0, "deaths": 9, "detectorWardsPlaced": 2, "doubleKills": 1, "dragonKills": 0, "eligibleForProgression": true, "enemyMissingPings": 28, "enemyVisionPings": 0, "firstBloodAssist": false, "firstBloodKill": false, "firstTowerAssist": false, "firstTowerKill": false, "gameEndedInEarlySurrender": false, "gameEndedInSurrender": false, "getBackPings": 0, "goldEarned": 11557, "goldSpent": 9620, "holdPings": 0, "individualPosition": "MIDDLE", "inhibitorKills": 0, "inhibitorTakedowns": 2, "inhibitorsLost": 0, "item0": 2421, "item1": 6657, "item2": 3040, "item3": 3191, "item4": 1056, "item5": 3158, "item6": 3363, "itemsPurchased": 22, "killingSprees": 1, "kills": 5, "lane": "MIDDLE", "largestCriticalStrike": 0, "largestKillingSpree": 5, "largestMultiKill": 2, "longestTimeSpentLiving": 263, "magicDamageDealt": 161406, "magicDamageDealtToChampions": 18127, "magicDamageTaken": 10626, "needVisionPings": 0, "neutralMinionsKilled": 20, "nexusKills": 0, "nexusLost": 0, "nexusTakedowns": 0, "objectivesStolen": 0, "objectivesStolenAssists": 0, "onMyWayPings": 1, "participantId": 3, "pentaKills": 0, "perks": {"statPerks": {"defense": 5002, "flex": 5008, "offense": 5005}, "styles": [{"description": "primaryStyle", "selections": [{"perk": 8230, "var1": 21, "var2": 0, "var3": 0}, {"perk": 8226, "var1": 250, "var2": 970, "var3": 0}, {"perk": 8210, "var1": 16, "var2": 0, "var3": 0}, {"perk": 8236, "var1": 24, "var2": 0, "var3": 0}], "style": 8200}, {"description": "subStyle", "selections": [{"perk": 8473, "var1": 1438, "var2": 0, "var3": 0}, {"perk": 8451, "var1": 228, "var2": 0, "var3": 0}], "style": 8400}]}, "physicalDamageDealt": 11120, "physicalDamageDealtToChampions": 773, "physicalDamageTaken": 20392, "profileIcon": 5335, "pushPings": 0, "puuid": "DjjA6Dq1BFAHFjNAi0Z6d9Ymuvkx3xAKuNnaoe20mU_pUQ4vuMH0UENx2c6UCwTOIjVhYrN6E1ryDw", "quadraKills": 0, "riotIdName": "", "riotIdTagline": "", "role": "SOLO", "sightWardsBoughtInGame": 0, "spell1Casts": 241, "spell2Casts": 61, "spell3Casts": 334, "spell4Casts": 3, "summoner1Casts": 4, "summoner1Id": 12, "summoner2Casts": 5, "summoner2Id": 4, "summonerId": "_dWpAvEy-zCSxxreXL4uHDx_XVkMBPJhDvVGYLBsNyTklLgeZQbyh1_zAQ", "summonerLevel": 73, "summonerName": "Szeregowy Sromek", "teamEarlySurrendered": false, "teamId": 100, "teamPosition": "MIDDLE", "timeCCingOthers": 26, "timePlayed": 1619, "totalDamageDealt": 172526, "totalDamageDealtToChampions": 18901, "totalDamageShieldedOnTeammates": 0, "totalDamageTaken": 32440, "totalHeal": 8126, "totalHealsOnTeammates": 0, "totalMinionsKilled": 196, "totalTimeCCDealt": 94, "totalTimeSpentDead": 237, "totalUnitsHealed": 1, "tripleKills": 0, "trueDamageDealt": 0, "trueDamageDealtToChampions": 0, "trueDamageTaken": 1421, "turretKills": 0, "turretTakedowns": 3, "turretsLost": 5, "unrealKills": 0, "visionClearedPings": 0, "visionScore": 21, "visionWardsBoughtInGame": 2, "wardsKilled": 1, "wardsPlaced": 8, "win": true}, {"allInPings": 2, "assistMePings": 9, "assists": 10, "baitPings": 0, "baronKills": 0, "basicPings": 0, "bountyLevel": 3, "challenges": {"12AssistStreakCount": 0, "abilityUses": 131, "acesBefore15Minutes": 0, "alliedJungleMonsterKills": 10.5, "baronBuffGoldAdvantageOverThreshold": 1, "baronTakedowns": 1, "blastConeOppositeOpponentCount": 0, "bountyGold": 0, "buffsStolen": 0, "completeSupportQuestInTime": 0, "controlWardTimeCoverageInRiverOrEnemyHalf": 0.44362745256242336, "controlWardsPlaced": 2, "damagePerMinute": 680.2945146812511, "damageTakenOnTeamPercentage": 0.13032610417985602, "dancedWithRiftHerald": 0, "deathsByEnemyChamps": 3, "dodgeSkillShotsSmallWindow": 0, "doubleAces": 0, "dragonTakedowns": 2, "earliestBaron": 1468.9055563454224, "earliestDragonTakedown": 456.3164047561301, "earlyLaningPhaseGoldExpAdvantage": 0, "effectiveHealAndShielding": 0, "elderDragonKillsWithOpposingSoul": 0, "elderDragonMultikills": 0, "enemyChampionImmobilizations": 10, "enemyJungleMonsterKills": 0, "epicMonsterKillsNearEnemyJungler": 0, "epicMonsterKillsWithin30SecondsOfSpawn": 0, "epicMonsterSteals": 0, "epicMonsterStolenWithoutSmite": 0, "firstTurretKilledTime": 927.1206063237158, "flawlessAces": 1, "fullTeamTakedown": 1, "gameLength": 1619.6166577078031, "getTakedownsInAllLanesEarlyJungleAsLaner": 0, "goldPerMinute": 475.5800572603539, "hadOpenNexus": 0, "immobilizeAndKillWithAlly": 4, "initialBuffCount": 0, "initialCrabCount": 0, "jungleCsBefore10Minutes": 0, "junglerTakedownsNearDamagedEpicMonster": 0, "kTurretsDestroyedBeforePlatesFall": 0, "kda": 6.333333333333333, "killAfterHiddenWithAlly": 4, "killParticipation": 0.6129032258064516, "killedChampTookFullTeamDamageSurvived": 0, "killingSprees": 2, "killsNearEnemyTurret": 1, "killsOnOtherLanesEarlyJungleAsLaner": 0, "killsOnRecentlyHealedByAramPack": 0, "killsUnderOwnTurret": 0, "killsWithHelpFromEpicMonster": 1, "knockEnemyIntoTeamAndKill": 4, "landSkillShotsEarlyGame": 2, "laneMinionsFirst10Minutes": 46, "laningPhaseGoldExpAdvantage": 0, "legendaryCount": 0, "lostAnInhibitor": 0, "maxCsAdvantageOnLaneOpponent": 3, "maxKillDeficit": 3, "maxLevelLeadLaneOpponent": 2, "moreEnemyJungleThanOpponent": 0, "multiKillOneSpell": 0, "multiTurretRiftHeraldCount": 0, "multikills": 2, "multikillsAfterAggressiveFlash": 1, "mythicItemUsed": 6673, "outerTurretExecutesBefore10Minutes": 0, "outnumberedKills": 0, "outnumberedNexusKill": 0, "perfectDragonSoulsTaken": 0, "perfectGame": 0, "pickKillWithAlly": 18, "playedChampSelectPosition": 1, "poroExplosions": 0, "quickCleanse": 0, "quickFirstTurret": 0, "quickSoloKills": 0, "riftHeraldTakedowns": 1, "saveAllyFromDeath": 0, "scuttleCrabKills": 0, "skillshotsDodged": 5, "skillshotsHit": 57, "snowballsHit": 0, "soloBaronKills": 0, "soloKills": 0, "soloTurretsLategame": 2, "stealthWardsPlaced": 5, "survivedSingleDigitHpCount": 1, "survivedThreeImmobilizesInFight": 0, "takedownOnFirstTurret": 1, "takedowns": 19, "takedownsAfterGainingLevelAdvantage": 0, "takedownsBeforeJungleMinionSpawn": 0, "takedownsFirstXMinutes": 7, "takedownsInAlcove": 1, "takedownsInEnemyFountain": 0, "teamBaronKills": 1, "teamDamagePercentage": 0.22895979268424524, "teamElderDragonKills": 0, "teamRiftHeraldKills": 2, "threeWardsOneSweeperCount": 0, "tookLargeDamageSurvived": 0, "turretPlatesTaken": 4, "turretTakedowns": 5, "turretsTakenWithRiftHerald": 5, "twentyMinionsIn3SecondsCount": 6, "unseenRecalls": 0, "visionScoreAdvantageLaneOpponent": 0.11386919021606445, "visionScorePerMinute": 0.7376422795499604, "wardTakedowns": 0, "wardTakedownsBefore20M": 0, "wardsGuarded": 0}, "champExperience": 12972, "champLevel": 14, "championId": 67, "championName": "Vayne", "championTransform": 0, "commandPings": 7, "consumablesPurchased": 3, "damageDealtToBuildings": 10095, "damageDealtToObjectives": 33571, "damageDealtToTurrets": 10095, "damageSelfMitigated": 11563, "dangerPings": 0, "deaths": 3, "detectorWardsPlaced": 2, "doubleKills": 2, "dragonKills": 1, "eligibleForProgression": true, "enemyMissingPings": 2, "enemyVisionPings": 0, "firstBloodAssist": false, "firstBloodKill": false, "firstTowerAssist": false, "firstTowerKill": true, "gameEndedInEarlySurrender": false, "gameEndedInSurrender": false, "getBackPings": 5, "goldEarned": 12837, "goldSpent": 11600, "holdPings": 1, "individualPosition": "BOTTOM", "inhibitorKills": 1, "inhibitorTakedowns": 1, "inhibitorsLost": 0, "item0": 3091, "item1": 3124, "item2": 1029, "item3": 1029, "item4": 3006, "item5": 6673, "item6": 3363, "itemsPurchased": 30, "killingSprees": 2, "kills": 9, "lane": "BOTTOM", "largestCriticalStrike": 283, "largestKillingSpree": 4, "largestMultiKill": 2, "longestTimeSpentLiving": 751, "magicDamageDealt": 3533, "magicDamageDealtToChampions": 448, "magicDamageTaken": 4709, "needVisionPings": 0, "neutralMinionsKilled": 16, "nexusKills": 1, "nexusLost": 0, "nexusTakedowns": 1, "objectivesStolen": 0, "objectivesStolenAssists": 0, "onMyWayPings": 0, "participantId": 4, "pentaKills": 0, "perks": {"statPerks": {"defense": 5002, "flex": 5008, "offense": 5005}, "styles": [{"description": "primaryStyle", "selections": [{"perk": 8008, "var1": 60, "var2": 4, "var3": 0}, {"perk": 9111, "var1": 694, "var2": 380, "var3": 0}, {"perk": 9104, "var1": 12, "var2": 40, "var3": 0}, {"perk": 8014, "var1": 412, "var2": 0, "var3": 0}], "style": 8000}, {"description": "subStyle", "selections": [{"perk": 8139, "var1": 543, "var2": 0, "var3": 0}, {"perk": 8135, "var1": 550, "var2": 5, "var3": 0}], "style": 8100}]}, "physicalDamageDealt": 104942, "physicalDamageDealtToChampions": 12217, "physicalDamageTaken": 9981, "profileIcon": 3150, "pushPings": 0, "puuid": "5zPeohIhsnYKveqPpjMCnUM0QDnfmrPxMq9oVdqbt1rqLlaIf25m3Q78FI9ENuSq7okhEdh-8cODJA", "quadraKills": 0, "riotIdName": "", "riotIdTagline": "", "role": "CARRY", "sightWardsBoughtInGame": 0, "spell1Casts": 113, "spell2Casts": 0, "spell3Casts": 10, "spell4Casts": 8, "summoner1Casts": 5, "summoner1Id": 3, "summoner2Casts": 4, "summoner2Id": 4, "summonerId": "suQxK1GoqxxFnHCDz8xnKtse9iRRIUUuGzcgKT0-S6xtoKU", "summonerLevel": 241, "summonerName": "Ciasny Szymu\u015b ", "teamEarlySurrendered": false, "teamId": 100, "teamPosition": "BOTTOM", "timeCCingOthers": 9, "timePlayed": 1619, "totalDamageDealt": 130178, "totalDamageDealtToChampions": 18363, "totalDamageShieldedOnTeammates": 0, "totalDamageTaken": 15873, "totalHeal": 3301, "totalHealsOnTeammates": 0, "totalMinionsKilled": 155, "totalTimeCCDealt": 49, "totalTimeSpentDead": 90, "totalUnitsHealed": 1, "tripleKills": 0, "trueDamageDealt": 21702, "trueDamageDealtToChampions": 5697, "trueDamageTaken": 1182, "turretKills": 5, "turretTakedowns": 5, "turretsLost": 5, "unrealKills": 0, "visionClearedPings": 0, "visionScore": 19, "visionWardsBoughtInGame": 2, "wardsKilled": 0, "wardsPlaced": 10, "win": true}, {"allInPings": 0, "assistMePings": 11, "assists": 18, "baitPings": 0, "baronKills": 0, "basicPings": 0, "bountyLevel": 4, "challenges": {"12AssistStreakCount": 0, "abilityUses": 106, "acesBefore15Minutes": 0, "alliedJungleMonsterKills": 0, "baronBuffGoldAdvantageOverThreshold": 1, "baronTakedowns": 1, "blastConeOppositeOpponentCount": 0, "bountyGold": 0, "buffsStolen": 0, "completeSupportQuestInTime": 1, "controlWardTimeCoverageInRiverOrEnemyHalf": 0.4271026133038691, "controlWardsPlaced": 5, "damagePerMinute": 368.3238466713912, "damageTakenOnTeamPercentage": 0.11653381251434024, "dancedWithRiftHerald": 0, "deathsByEnemyChamps": 0, "dodgeSkillShotsSmallWindow": 2, "doubleAces": 0, "dragonTakedowns": 2, "earliestBaron": 1468.9055563454224, "earliestDragonTakedown": 456.3164047561301, "earlyLaningPhaseGoldExpAdvantage": 0, "effectiveHealAndShielding": 1437.2371826171875, "elderDragonKillsWithOpposingSoul": 0, "elderDragonMultikills": 0, "enemyChampionImmobilizations": 57, "enemyJungleMonsterKills": 0, "epicMonsterKillsNearEnemyJungler": 0, "epicMonsterKillsWithin30SecondsOfSpawn": 0, "epicMonsterSteals": 0, "epicMonsterStolenWithoutSmite": 0, "firstTurretKilledTime": 927.1206063237158, "flawlessAces": 1, "fullTeamTakedown": 1, "gameLength": 1619.6166577078031, "getTakedownsInAllLanesEarlyJungleAsLaner": 0, "goldPerMinute": 351.31016358773564, "hadOpenNexus": 0, "highestCrowdControlScore": 1, "immobilizeAndKillWithAlly": 21, "initialBuffCount": 0, "initialCrabCount": 0, "jungleCsBefore10Minutes": 0, "junglerTakedownsNearDamagedEpicMonster": 0, "kTurretsDestroyedBeforePlatesFall": 0, "kda": 22, "killAfterHiddenWithAlly": 4, "killParticipation": 0.7096774193548387, "killedChampTookFullTeamDamageSurvived": 0, "killingSprees": 1, "killsNearEnemyTurret": 1, "killsOnOtherLanesEarlyJungleAsLaner": 0, "killsOnRecentlyHealedByAramPack": 0, "killsUnderOwnTurret": 1, "killsWithHelpFromEpicMonster": 0, "knockEnemyIntoTeamAndKill": 13, "landSkillShotsEarlyGame": 3, "laneMinionsFirst10Minutes": 14, "laningPhaseGoldExpAdvantage": 0, "legendaryCount": 0, "lostAnInhibitor": 0, "maxCsAdvantageOnLaneOpponent": 21, "maxKillDeficit": 3, "maxLevelLeadLaneOpponent": 3, "moreEnemyJungleThanOpponent": 0, "multiKillOneSpell": 0, "multiTurretRiftHeraldCount": 0, "multikills": 0, "multikillsAfterAggressiveFlash": 0, "mythicItemUsed": 3190, "outerTurretExecutesBefore10Minutes": 0, "outnumberedKills": 0, "outnumberedNexusKill": 0, "perfectDragonSoulsTaken": 0, "perfectGame": 0, "pickKillWithAlly": 20, "playedChampSelectPosition": 1, "poroExplosions": 0, "quickCleanse": 0, "quickFirstTurret": 0, "quickSoloKills": 0, "riftHeraldTakedowns": 1, "saveAllyFromDeath": 0, "scuttleCrabKills": 0, "shortestTimeToAceFromFirstTakedown": 23.698614962239844, "skillshotsDodged": 15, "skillshotsHit": 17, "snowballsHit": 0, "soloBaronKills": 0, "soloKills": 0, "stealthWardsPlaced": 26, "survivedSingleDigitHpCount": 0, "survivedThreeImmobilizesInFight": 2, "takedownOnFirstTurret": 0, "takedowns": 22, "takedownsAfterGainingLevelAdvantage": 0, "takedownsBeforeJungleMinionSpawn": 0, "takedownsFirstXMinutes": 7, "takedownsInAlcove": 1, "takedownsInEnemyFountain": 0, "teamBaronKills": 1, "teamDamagePercentage": 0.12396300389700854, "teamElderDragonKills": 0, "teamRiftHeraldKills": 2, "threeWardsOneSweeperCount": 0, "tookLargeDamageSurvived": 0, "turretPlatesTaken": 4, "turretTakedowns": 4, "turretsTakenWithRiftHerald": 5, "twentyMinionsIn3SecondsCount": 1, "unseenRecalls": 0, "visionScoreAdvantageLaneOpponent": -0.29313695430755615, "visionScorePerMinute": 2.1268943821755335, "wardTakedowns": 3, "wardTakedownsBefore20M": 3, "wardsGuarded": 1}, "champExperience": 12657, "champLevel": 14, "championId": 53, "championName": "Blitzcrank", "championTransform": 0, "commandPings": 34, "consumablesPurchased": 8, "damageDealtToBuildings": 1708, "damageDealtToObjectives": 8807, "damageDealtToTurrets": 1708, "damageSelfMitigated": 16916, "dangerPings": 0, "deaths": 0, "detectorWardsPlaced": 5, "doubleKills": 0, "dragonKills": 0, "eligibleForProgression": true, "enemyMissingPings": 7, "enemyVisionPings": 0, "firstBloodAssist": false, "firstBloodKill": false, "firstTowerAssist": true, "firstTowerKill": false, "gameEndedInEarlySurrender": false, "gameEndedInSurrender": false, "getBackPings": 0, "goldEarned": 9483, "goldSpent": 7950, "holdPings": 1, "individualPosition": "UTILITY", "inhibitorKills": 0, "inhibitorTakedowns": 2, "inhibitorsLost": 0, "item0": 3117, "item1": 3190, "item2": 3860, "item3": 2055, "item4": 3801, "item5": 3110, "item6": 3364, "itemsPurchased": 23, "killingSprees": 1, "kills": 4, "lane": "BOTTOM", "largestCriticalStrike": 0, "largestKillingSpree": 4, "largestMultiKill": 1, "longestTimeSpentLiving": 0, "magicDamageDealt": 12306, "magicDamageDealtToChampions": 5792, "magicDamageTaken": 6460, "needVisionPings": 0, "neutralMinionsKilled": 0, "nexusKills": 0, "nexusLost": 0, "nexusTakedowns": 1, "objectivesStolen": 0, "objectivesStolenAssists": 0, "onMyWayPings": 17, "participantId": 5, "pentaKills": 0, "perks": {"statPerks": {"defense": 5002, "flex": 5002, "offense": 5007}, "styles": [{"description": "primaryStyle", "selections": [{"perk": 8351, "var1": 51, "var2": 1410, "var3": 0}, {"perk": 8306, "var1": 0, "var2": 0, "var3": 0}, {"perk": 8345, "var1": 3, "var2": 0, "var3": 0}, {"perk": 8347, "var1": 0, "var2": 0, "var3": 0}], "style": 8300}, {"description": "subStyle", "selections": [{"perk": 8473, "var1": 765, "var2": 0, "var3": 0}, {"perk": 8242, "var1": 6, "var2": 0, "var3": 0}], "style": 8400}]}, "physicalDamageDealt": 10880, "physicalDamageDealtToChampions": 2955, "physicalDamageTaken": 7524, "profileIcon": 3796, "pushPings": 0, "puuid": "KVrHIDsUfkjhE0TAROUdnTFqBgacRUT4VCaTLXZny2d2T3ZrplCH9OHACSUTcu-pDuqP8tl2MCHqAQ", "quadraKills": 0, "riotIdName": "", "riotIdTagline": "", "role": "SUPPORT", "sightWardsBoughtInGame": 0, "spell1Casts": 24, "spell2Casts": 25, "spell3Casts": 46, "spell4Casts": 11, "summoner1Casts": 2, "summoner1Id": 4, "summoner2Casts": 6, "summoner2Id": 14, "summonerId": "vIU-3ipkcUr3gGd_PMYztlTHixFQ4hkxA0mLxDKGvH-kQhI", "summonerLevel": 301, "summonerName": "Fr\u00e9\u00e8ze", "teamEarlySurrendered": false, "teamId": 100, "teamPosition": "UTILITY", "timeCCingOthers": 46, "timePlayed": 1619, "totalDamageDealt": 34112, "totalDamageDealtToChampions": 9942, "totalDamageShieldedOnTeammates": 1437, "totalDamageTaken": 14193, "totalHeal": 3130, "totalHealsOnTeammates": 0, "totalMinionsKilled": 32, "totalTimeCCDealt": 361, "totalTimeSpentDead": 0, "totalUnitsHealed": 1, "tripleKills": 0, "trueDamageDealt": 10925, "trueDamageDealtToChampions": 1194, "trueDamageTaken": 208, "turretKills": 0, "turretTakedowns": 4, "turretsLost": 5, "unrealKills": 0, "visionClearedPings": 0, "visionScore": 57, "visionWardsBoughtInGame": 6, "wardsKilled": 3, "wardsPlaced": 31, "win": true}, {"allInPings": 1, "assistMePings": 4, "assists": 1, "baitPings": 3, "baronKills": 0, "basicPings": 0, "bountyLevel": 0, "challenges": {"12AssistStreakCount": 0, "abilityUses": 242, "acesBefore15Minutes": 0, "alliedJungleMonsterKills": 0, "baronTakedowns": 0, "blastConeOppositeOpponentCount": 0, "bountyGold": 0, "buffsStolen": 0, "completeSupportQuestInTime": 0, "controlWardsPlaced": 0, "damagePerMinute": 804.086683908972, "damageTakenOnTeamPercentage": 0.22767311628100187, "dancedWithRiftHerald": 0, "deathsByEnemyChamps": 7, "dodgeSkillShotsSmallWindow": 1, "doubleAces": 0, "dragonTakedowns": 0, "earlyLaningPhaseGoldExpAdvantage": 0, "effectiveHealAndShielding": 0, "elderDragonKillsWithOpposingSoul": 0, "elderDragonMultikills": 0, "enemyChampionImmobilizations": 25, "enemyJungleMonsterKills": 0, "epicMonsterKillsNearEnemyJungler": 0, "epicMonsterKillsWithin30SecondsOfSpawn": 0, "epicMonsterSteals": 0, "epicMonsterStolenWithoutSmite": 0, "flawlessAces": 0, "fullTeamTakedown": 0, "gameLength": 1619.6166577078031, "getTakedownsInAllLanesEarlyJungleAsLaner": 0, "goldPerMinute": 416.43194639776306, "hadOpenNexus": 0, "immobilizeAndKillWithAlly": 0, "initialBuffCount": 0, "initialCrabCount": 0, "jungleCsBefore10Minutes": 4, "junglerTakedownsNearDamagedEpicMonster": 0, "kTurretsDestroyedBeforePlatesFall": 0, "kda": 0.7142857142857143, "killAfterHiddenWithAlly": 0, "killParticipation": 0.25, "killedChampTookFullTeamDamageSurvived": 0, "killsNearEnemyTurret": 2, "killsOnOtherLanesEarlyJungleAsLaner": 0, "killsOnRecentlyHealedByAramPack": 0, "killsUnderOwnTurret": 0, "killsWithHelpFromEpicMonster": 0, "knockEnemyIntoTeamAndKill": 2, "landSkillShotsEarlyGame": 0, "laneMinionsFirst10Minutes": 95, "laningPhaseGoldExpAdvantage": 0, "legendaryCount": 0, "lostAnInhibitor": 0, "maxCsAdvantageOnLaneOpponent": 40, "maxKillDeficit": 0, "maxLevelLeadLaneOpponent": 2, "moreEnemyJungleThanOpponent": 0, "multiKillOneSpell": 0, "multiTurretRiftHeraldCount": 0, "multikills": 0, "multikillsAfterAggressiveFlash": 0, "mythicItemUsed": 6665, "outerTurretExecutesBefore10Minutes": 0, "outnumberedKills": 3, "outnumberedNexusKill": 0, "perfectDragonSoulsTaken": 0, "perfectGame": 0, "pickKillWithAlly": 1, "playedChampSelectPosition": 1, "poroExplosions": 0, "quickCleanse": 0, "quickFirstTurret": 0, "quickSoloKills": 0, "riftHeraldTakedowns": 0, "saveAllyFromDeath": 0, "scuttleCrabKills": 1, "skillshotsDodged": 14, "skillshotsHit": 0, "snowballsHit": 0, "soloBaronKills": 0, "soloKills": 4, "soloTurretsLategame": 1, "stealthWardsPlaced": 7, "survivedSingleDigitHpCount": 0, "survivedThreeImmobilizesInFight": 2, "takedownOnFirstTurret": 0, "takedowns": 5, "takedownsAfterGainingLevelAdvantage": 0, "takedownsBeforeJungleMinionSpawn": 0, "takedownsFirstXMinutes": 3, "takedownsInAlcove": 0, "takedownsInEnemyFountain": 0, "teamBaronKills": 0, "teamDamagePercentage": 0.2532909629732819, "teamElderDragonKills": 0, "teamRiftHeraldKills": 2, "threeWardsOneSweeperCount": 0, "tookLargeDamageSurvived": 0, "turretPlatesTaken": 4, "turretTakedowns": 2, "turretsTakenWithRiftHerald": 0, "twentyMinionsIn3SecondsCount": 9, "unseenRecalls": 0, "visionScoreAdvantageLaneOpponent": 0.11555695533752441, "visionScorePerMinute": 0.5279406046382815, "wardTakedowns": 2, "wardTakedownsBefore20M": 0, "wardsGuarded": 0}, "champExperience": 13331, "champLevel": 15, "championId": 82, "championName": "Mordekaiser", "championTransform": 0, "commandPings": 8, "consumablesPurchased": 1, "damageDealtToBuildings": 4112, "damageDealtToObjectives": 4980, "damageDealtToTurrets": 4112, "damageSelfMitigated": 34021, "dangerPings": 0, "deaths": 7, "detectorWardsPlaced": 0, "doubleKills": 0, "dragonKills": 0, "eligibleForProgression": true, "enemyMissingPings": 3, "enemyVisionPings": 1, "firstBloodAssist": false, "firstBloodKill": false, "firstTowerAssist": false, "firstTowerKill": false, "gameEndedInEarlySurrender": false, "gameEndedInSurrender": false, "getBackPings": 0, "goldEarned": 11241, "goldSpent": 9585, "holdPings": 0, "individualPosition": "TOP", "inhibitorKills": 0, "inhibitorTakedowns": 0, "inhibitorsLost": 2, "item0": 3047, "item1": 3116, "item2": 6665, "item3": 1026, "item4": 1052, "item5": 1011, "item6": 3340, "itemsPurchased": 17, "killingSprees": 1, "kills": 4, "lane": "MIDDLE", "largestCriticalStrike": 0, "largestKillingSpree": 2, "largestMultiKill": 1, "longestTimeSpentLiving": 331, "magicDamageDealt": 116683, "magicDamageDealtToChampions": 18332, "magicDamageTaken": 8626, "needVisionPings": 0, "neutralMinionsKilled": 4, "nexusKills": 0, "nexusLost": 1, "nexusTakedowns": 0, "objectivesStolen": 0, "objectivesStolenAssists": 0, "onMyWayPings": 11, "participantId": 6, "pentaKills": 0, "perks": {"statPerks": {"defense": 5002, "flex": 5008, "offense": 5005}, "styles": [{"description": "primaryStyle", "selections": [{"perk": 8010, "var1": 761, "var2": 0, "var3": 0}, {"perk": 9111, "var1": 482, "var2": 100, "var3": 0}, {"perk": 9105, "var1": 19, "var2": 10, "var3": 0}, {"perk": 8299, "var1": 835, "var2": 0, "var3": 0}], "style": 8000}, {"description": "subStyle", "selections": [{"perk": 8473, "var1": 438, "var2": 0, "var3": 0}, {"perk": 8453, "var1": 346, "var2": 1078, "var3": 0}], "style": 8400}]}, "physicalDamageDealt": 22040, "physicalDamageDealtToChampions": 2410, "physicalDamageTaken": 13252, "profileIcon": 5533, "pushPings": 1, "puuid": "1Pavvm2ONGKUD_YKXMvTUQyEVHtNxxGhtBSu7-GFyLh95UG0ORPlpSpZ9oZeUm1Kye0QjH_soaeLow", "quadraKills": 0, "riotIdName": "", "riotIdTagline": "", "role": "CARRY", "sightWardsBoughtInGame": 0, "spell1Casts": 124, "spell2Casts": 52, "spell3Casts": 62, "spell4Casts": 4, "summoner1Casts": 3, "summoner1Id": 4, "summoner2Casts": 4, "summoner2Id": 14, "summonerId": "5PrFcLmHwF9z23wK7Y3QQhymuw9ee9h4h7Z_AUj8e6WQxhM", "summonerLevel": 160, "summonerName": "General Trifut", "teamEarlySurrendered": false, "teamId": 200, "teamPosition": "TOP", "timeCCingOthers": 26, "timePlayed": 1619, "totalDamageDealt": 148173, "totalDamageDealtToChampions": 21705, "totalDamageShieldedOnTeammates": 0, "totalDamageTaken": 24813, "totalHeal": 4609, "totalHealsOnTeammates": 0, "totalMinionsKilled": 209, "totalTimeCCDealt": 362, "totalTimeSpentDead": 254, "totalUnitsHealed": 1, "tripleKills": 0, "trueDamageDealt": 9449, "trueDamageDealtToChampions": 962, "trueDamageTaken": 2933, "turretKills": 2, "turretTakedowns": 2, "turretsLost": 10, "unrealKills": 0, "visionClearedPings": 0, "visionScore": 14, "visionWardsBoughtInGame": 0, "wardsKilled": 2, "wardsPlaced": 7, "win": false}, {"allInPings": 7, "assistMePings": 0, "assists": 4, "baitPings": 0, "baronKills": 0, "basicPings": 0, "bountyLevel": 0, "challenges": {"12AssistStreakCount": 0, "abilityUses": 193, "acesBefore15Minutes": 0, "alliedJungleMonsterKills": 115.10000020265579, "baronTakedowns": 0, "blastConeOppositeOpponentCount": 0, "bountyGold": 0, "buffsStolen": 0, "completeSupportQuestInTime": 0, "controlWardsPlaced": 0, "damagePerMinute": 546.1490926011043, "damageTakenOnTeamPercentage": 0.2813831021525533, "dancedWithRiftHerald": 0, "deathsByEnemyChamps": 4, "dodgeSkillShotsSmallWindow": 3, "doubleAces": 0, "dragonTakedowns": 1, "earliestDragonTakedown": 1103.791989635596, "earlyLaningPhaseGoldExpAdvantage": 0, "effectiveHealAndShielding": 0, "elderDragonKillsWithOpposingSoul": 0, "elderDragonMultikills": 0, "enemyChampionImmobilizations": 8, "enemyJungleMonsterKills": 0.5, "epicMonsterKillsNearEnemyJungler": 0, "epicMonsterKillsWithin30SecondsOfSpawn": 1, "epicMonsterSteals": 0, "epicMonsterStolenWithoutSmite": 0, "flawlessAces": 0, "fullTeamTakedown": 0, "gameLength": 1619.6166577078031, "goldPerMinute": 395.9603776520298, "hadOpenNexus": 0, "immobilizeAndKillWithAlly": 1, "initialBuffCount": 1, "initialCrabCount": 1, "jungleCsBefore10Minutes": 52.00000008940697, "junglerKillsEarlyJungle": 0, "junglerTakedownsNearDamagedEpicMonster": 0, "kTurretsDestroyedBeforePlatesFall": 0, "kda": 2.25, "killAfterHiddenWithAlly": 1, "killParticipation": 0.45, "killedChampTookFullTeamDamageSurvived": 0, "killingSprees": 1, "killsNearEnemyTurret": 1, "killsOnLanersEarlyJungleAsJungler": 2, "killsOnRecentlyHealedByAramPack": 0, "killsUnderOwnTurret": 0, "killsWithHelpFromEpicMonster": 0, "knockEnemyIntoTeamAndKill": 0, "landSkillShotsEarlyGame": 2, "laneMinionsFirst10Minutes": 5, "laningPhaseGoldExpAdvantage": 0, "legendaryCount": 0, "lostAnInhibitor": 0, "maxCsAdvantageOnLaneOpponent": 62.10000005364418, "maxKillDeficit": 0, "maxLevelLeadLaneOpponent": 2, "moreEnemyJungleThanOpponent": -37.000000059604645, "multiKillOneSpell": 0, "multiTurretRiftHeraldCount": 0, "multikills": 0, "multikillsAfterAggressiveFlash": 0, "mythicItemUsed": 3152, "outerTurretExecutesBefore10Minutes": 0, "outnumberedKills": 1, "outnumberedNexusKill": 0, "perfectDragonSoulsTaken": 0, "perfectGame": 0, "pickKillWithAlly": 7, "playedChampSelectPosition": 1, "poroExplosions": 0, "quickCleanse": 0, "quickFirstTurret": 0, "quickSoloKills": 0, "riftHeraldTakedowns": 2, "saveAllyFromDeath": 0, "scuttleCrabKills": 4, "skillshotsDodged": 22, "skillshotsHit": 36, "snowballsHit": 0, "soloBaronKills": 0, "soloKills": 1, "stealthWardsPlaced": 0, "survivedSingleDigitHpCount": 0, "survivedThreeImmobilizesInFight": 0, "takedownOnFirstTurret": 0, "takedowns": 9, "takedownsAfterGainingLevelAdvantage": 0, "takedownsBeforeJungleMinionSpawn": 0, "takedownsFirstXMinutes": 7, "takedownsInAlcove": 0, "takedownsInEnemyFountain": 0, "teamBaronKills": 0, "teamDamagePercentage": 0.17203944843287347, "teamElderDragonKills": 0, "teamRiftHeraldKills": 2, "threeWardsOneSweeperCount": 0, "tookLargeDamageSurvived": 0, "turretPlatesTaken": 2, "turretTakedowns": 0, "turretsTakenWithRiftHerald": 0, "twentyMinionsIn3SecondsCount": 2, "unseenRecalls": 0, "visionScoreAdvantageLaneOpponent": 0.4409217834472656, "visionScorePerMinute": 0.7038702612588643, "wardTakedowns": 6, "wardTakedownsBefore20M": 5, "wardsGuarded": 0}, "champExperience": 12450, "champLevel": 14, "championId": 245, "championName": "Ekko", "championTransform": 0, "commandPings": 1, "consumablesPurchased": 0, "damageDealtToBuildings": 84, "damageDealtToObjectives": 21056, "damageDealtToTurrets": 84, "damageSelfMitigated": 19640, "dangerPings": 0, "deaths": 4, "detectorWardsPlaced": 0, "doubleKills": 0, "dragonKills": 1, "eligibleForProgression": true, "enemyMissingPings": 13, "enemyVisionPings": 0, "firstBloodAssist": false, "firstBloodKill": false, "firstTowerAssist": false, "firstTowerKill": false, "gameEndedInEarlySurrender": false, "gameEndedInSurrender": false, "getBackPings": 0, "goldEarned": 10688, "goldSpent": 10300, "holdPings": 0, "individualPosition": "JUNGLE", "inhibitorKills": 0, "inhibitorTakedowns": 0, "inhibitorsLost": 2, "item0": 3152, "item1": 1082, "item2": 3115, "item3": 3020, "item4": 1058, "item5": 1058, "item6": 3364, "itemsPurchased": 15, "killingSprees": 1, "kills": 5, "lane": "JUNGLE", "largestCriticalStrike": 0, "largestKillingSpree": 5, "largestMultiKill": 1, "longestTimeSpentLiving": 1104, "magicDamageDealt": 162367, "magicDamageDealtToChampions": 11820, "magicDamageTaken": 15446, "needVisionPings": 0, "neutralMinionsKilled": 144, "nexusKills": 0, "nexusLost": 1, "nexusTakedowns": 0, "objectivesStolen": 0, "objectivesStolenAssists": 0, "onMyWayPings": 19, "participantId": 7, "pentaKills": 0, "perks": {"statPerks": {"defense": 5002, "flex": 5008, "offense": 5005}, "styles": [{"description": "primaryStyle", "selections": [{"perk": 8128, "var1": 826, "var2": 11, "var3": 0}, {"perk": 8143, "var1": 621, "var2": 0, "var3": 0}, {"perk": 8138, "var1": 18, "var2": 0, "var3": 0}, {"perk": 8135, "var1": 270, "var2": 3, "var3": 0}], "style": 8100}, {"description": "subStyle", "selections": [{"perk": 8304, "var1": 9, "var2": 0, "var3": 0}, {"perk": 8347, "var1": 0, "var2": 0, "var3": 0}], "style": 8300}]}, "physicalDamageDealt": 31018, "physicalDamageDealtToChampions": 1318, "physicalDamageTaken": 14405, "profileIcon": 4928, "pushPings": 1, "puuid": "nwiIR1_T4TBsUucBfIUPWyGWwKXOpWywFHNbaz4V8THiv8o2XvXeWT-csMLWp-CZXJGIUDRDUVcHsw", "quadraKills": 0, "riotIdName": "", "riotIdTagline": "", "role": "NONE", "sightWardsBoughtInGame": 0, "spell1Casts": 99, "spell2Casts": 23, "spell3Casts": 67, "spell4Casts": 4, "summoner1Casts": 3, "summoner1Id": 4, "summoner2Casts": 17, "summoner2Id": 11, "summonerId": "t95hnw5u0KXOtbF0LBUR_ILxZdhPdh9nkpOYh6lJGTKna8c", "summonerLevel": 388, "summonerName": "stoic ekko", "teamEarlySurrendered": false, "teamId": 200, "teamPosition": "JUNGLE", "timeCCingOthers": 20, "timePlayed": 1619, "totalDamageDealt": 231932, "totalDamageDealtToChampions": 14742, "totalDamageShieldedOnTeammates": 0, "totalDamageTaken": 30667, "totalHeal": 2842, "totalHealsOnTeammates": 0, "totalMinionsKilled": 55, "totalTimeCCDealt": 490, "totalTimeSpentDead": 97, "totalUnitsHealed": 1, "tripleKills": 0, "trueDamageDealt": 38547, "trueDamageDealtToChampions": 1602, "trueDamageTaken": 815, "turretKills": 0, "turretTakedowns": 0, "turretsLost": 10, "unrealKills": 0, "visionClearedPings": 0, "visionScore": 19, "visionWardsBoughtInGame": 0, "wardsKilled": 6, "wardsPlaced": 0, "win": false}, {"allInPings": 1, "assistMePings": 2, "assists": 3, "baitPings": 0, "baronKills": 0, "basicPings": 0, "bountyLevel": 0, "challenges": {"12AssistStreakCount": 0, "abilityUses": 279, "acesBefore15Minutes": 0, "alliedJungleMonsterKills": 0, "baronTakedowns": 0, "blastConeOppositeOpponentCount": 0, "bountyGold": 375, "buffsStolen": 0, "completeSupportQuestInTime": 0, "controlWardTimeCoverageInRiverOrEnemyHalf": 0.3249370304983856, "controlWardsPlaced": 2, "damagePerMinute": 822.7097249578876, "damageTakenOnTeamPercentage": 0.18274160861666103, "dancedWithRiftHerald": 0, "deathsByEnemyChamps": 5, "dodgeSkillShotsSmallWindow": 8, "doubleAces": 0, "dragonTakedowns": 1, "earliestDragonTakedown": 1103.791989635596, "earlyLaningPhaseGoldExpAdvantage": 0, "effectiveHealAndShielding": 0, "elderDragonKillsWithOpposingSoul": 0, "elderDragonMultikills": 0, "enemyChampionImmobilizations": 0, "enemyJungleMonsterKills": 0, "epicMonsterKillsNearEnemyJungler": 0, "epicMonsterKillsWithin30SecondsOfSpawn": 0, "epicMonsterSteals": 0, "epicMonsterStolenWithoutSmite": 0, "flawlessAces": 0, "fullTeamTakedown": 0, "gameLength": 1619.6166577078031, "getTakedownsInAllLanesEarlyJungleAsLaner": 0, "goldPerMinute": 379.6084541704994, "hadOpenNexus": 0, "immobilizeAndKillWithAlly": 0, "initialBuffCount": 0, "initialCrabCount": 0, "jungleCsBefore10Minutes": 0, "junglerTakedownsNearDamagedEpicMonster": 0, "kTurretsDestroyedBeforePlatesFall": 0, "kda": 2.2, "killAfterHiddenWithAlly": 1, "killParticipation": 0.55, "killedChampTookFullTeamDamageSurvived": 0, "killingSprees": 1, "killsNearEnemyTurret": 3, "killsOnOtherLanesEarlyJungleAsLaner": 1, "killsOnRecentlyHealedByAramPack": 0, "killsUnderOwnTurret": 2, "killsWithHelpFromEpicMonster": 0, "knockEnemyIntoTeamAndKill": 0, "landSkillShotsEarlyGame": 16, "laneMinionsFirst10Minutes": 46, "laningPhaseGoldExpAdvantage": 1, "legendaryCount": 0, "lostAnInhibitor": 0, "maxCsAdvantageOnLaneOpponent": 8.999999970197678, "maxKillDeficit": 0, "maxLevelLeadLaneOpponent": 3, "moreEnemyJungleThanOpponent": 0, "multiKillOneSpell": 0, "multiTurretRiftHeraldCount": 0, "multikills": 0, "multikillsAfterAggressiveFlash": 0, "outerTurretExecutesBefore10Minutes": 0, "outnumberedKills": 1, "outnumberedNexusKill": 0, "perfectDragonSoulsTaken": 0, "perfectGame": 0, "pickKillWithAlly": 7, "playedChampSelectPosition": 1, "poroExplosions": 0, "quickCleanse": 0, "quickFirstTurret": 0, "quickSoloKills": 0, "riftHeraldTakedowns": 0, "saveAllyFromDeath": 0, "scuttleCrabKills": 0, "skillshotsDodged": 42, "skillshotsHit": 60, "snowballsHit": 0, "soloBaronKills": 0, "soloKills": 3, "stealthWardsPlaced": 4, "survivedSingleDigitHpCount": 0, "survivedThreeImmobilizesInFight": 2, "takedownOnFirstTurret": 0, "takedowns": 11, "takedownsAfterGainingLevelAdvantage": 0, "takedownsBeforeJungleMinionSpawn": 0, "takedownsFirstXMinutes": 7, "takedownsInAlcove": 0, "takedownsInEnemyFountain": 0, "teamBaronKills": 0, "teamDamagePercentage": 0.25915730561415173, "teamElderDragonKills": 0, "teamRiftHeraldKills": 2, "threeWardsOneSweeperCount": 0, "tookLargeDamageSurvived": 0, "turretPlatesTaken": 1, "turretTakedowns": 1, "turretsTakenWithRiftHerald": 0, "twentyMinionsIn3SecondsCount": 7, "unseenRecalls": 0, "visionScoreAdvantageLaneOpponent": 0.558219313621521, "visionScorePerMinute": 1.2297509717578712, "wardTakedowns": 4, "wardTakedownsBefore20M": 2, "wardsGuarded": 0}, "champExperience": 13579, "champLevel": 15, "championId": 238, "championName": "Zed", "championTransform": 0, "commandPings": 3, "consumablesPurchased": 3, "damageDealtToBuildings": 1943, "damageDealtToObjectives": 4638, "damageDealtToTurrets": 1943, "damageSelfMitigated": 11873, "dangerPings": 0, "deaths": 5, "detectorWardsPlaced": 2, "doubleKills": 0, "dragonKills": 0, "eligibleForProgression": true, "enemyMissingPings": 2, "enemyVisionPings": 1, "firstBloodAssist": false, "firstBloodKill": false, "firstTowerAssist": false, "firstTowerKill": false, "gameEndedInEarlySurrender": false, "gameEndedInSurrender": false, "getBackPings": 0, "goldEarned": 10247, "goldSpent": 11855, "holdPings": 3, "individualPosition": "MIDDLE", "inhibitorKills": 0, "inhibitorTakedowns": 0, "inhibitorsLost": 2, "item0": 6693, "item1": 3035, "item2": 3074, "item3": 3158, "item4": 1036, "item5": 2055, "item6": 3364, "itemsPurchased": 25, "killingSprees": 2, "kills": 8, "lane": "MIDDLE", "largestCriticalStrike": 0, "largestKillingSpree": 6, "largestMultiKill": 1, "longestTimeSpentLiving": 1271, "magicDamageDealt": 5595, "magicDamageDealtToChampions": 1580, "magicDamageTaken": 12921, "needVisionPings": 0, "neutralMinionsKilled": 0, "nexusKills": 0, "nexusLost": 1, "nexusTakedowns": 0, "objectivesStolen": 0, "objectivesStolenAssists": 0, "onMyWayPings": 6, "participantId": 8, "pentaKills": 0, "perks": {"statPerks": {"defense": 5003, "flex": 5008, "offense": 5008}, "styles": [{"description": "primaryStyle", "selections": [{"perk": 8112, "var1": 1653, "var2": 0, "var3": 0}, {"perk": 8139, "var1": 871, "var2": 0, "var3": 0}, {"perk": 8138, "var1": 18, "var2": 0, "var3": 0}, {"perk": 8106, "var1": 3, "var2": 0, "var3": 0}], "style": 8100}, {"description": "subStyle", "selections": [{"perk": 8210, "var1": 7, "var2": 0, "var3": 0}, {"perk": 8237, "var1": 682, "var2": 0, "var3": 0}], "style": 8200}]}, "physicalDamageDealt": 115595, "physicalDamageDealtToChampions": 19676, "physicalDamageTaken": 6147, "profileIcon": 657, "pushPings": 0, "puuid": "ajcnX3-CQTwe5VDcY6U5DyBSksUQEMj7g65xcDMlwg8z2DgUc0JEu-_mmfu76ZDn8il9lXoK7OhEwA", "quadraKills": 0, "riotIdName": "", "riotIdTagline": "", "role": "SUPPORT", "sightWardsBoughtInGame": 0, "spell1Casts": 89, "spell2Casts": 80, "spell3Casts": 90, "spell4Casts": 20, "summoner1Casts": 5, "summoner1Id": 14, "summoner2Casts": 2, "summoner2Id": 4, "summonerId": "ss60WIK2PHneJ3WQveUryMBG8HTj_rNQlqx3jmAPs9s4g28", "summonerLevel": 262, "summonerName": "blvck", "teamEarlySurrendered": false, "teamId": 200, "teamPosition": "MIDDLE", "timeCCingOthers": 7, "timePlayed": 1619, "totalDamageDealt": 122140, "totalDamageDealtToChampions": 22207, "totalDamageShieldedOnTeammates": 0, "totalDamageTaken": 19916, "totalHeal": 3051, "totalHealsOnTeammates": 0, "totalMinionsKilled": 167, "totalTimeCCDealt": 109, "totalTimeSpentDead": 184, "totalUnitsHealed": 1, "tripleKills": 0, "trueDamageDealt": 950, "trueDamageDealtToChampions": 950, "trueDamageTaken": 848, "turretKills": 1, "turretTakedowns": 1, "turretsLost": 10, "unrealKills": 0, "visionClearedPings": 0, "visionScore": 33, "visionWardsBoughtInGame": 3, "wardsKilled": 4, "wardsPlaced": 6, "win": false}, {"allInPings": 0, "assistMePings": 15, "assists": 4, "baitPings": 0, "baronKills": 0, "basicPings": 0, "bountyLevel": 0, "challenges": {"12AssistStreakCount": 0, "abilityUses": 147, "acesBefore15Minutes": 0, "alliedJungleMonsterKills": 8, "baronTakedowns": 0, "blastConeOppositeOpponentCount": 0, "bountyGold": 0, "buffsStolen": 0, "completeSupportQuestInTime": 0, "controlWardsPlaced": 0, "damagePerMinute": 712.6765262288021, "damageTakenOnTeamPercentage": 0.19213417708155553, "dancedWithRiftHerald": 0, "deathsByEnemyChamps": 9, "dodgeSkillShotsSmallWindow": 7, "doubleAces": 0, "dragonTakedowns": 0, "earlyLaningPhaseGoldExpAdvantage": 0, "effectiveHealAndShielding": 0, "elderDragonKillsWithOpposingSoul": 0, "elderDragonMultikills": 0, "enemyChampionImmobilizations": 0, "enemyJungleMonsterKills": 0, "epicMonsterKillsNearEnemyJungler": 0, "epicMonsterKillsWithin30SecondsOfSpawn": 0, "epicMonsterSteals": 0, "epicMonsterStolenWithoutSmite": 0, "flawlessAces": 0, "fullTeamTakedown": 0, "gameLength": 1619.6166577078031, "getTakedownsInAllLanesEarlyJungleAsLaner": 0, "goldPerMinute": 375.3456905493095, "hadOpenNexus": 0, "immobilizeAndKillWithAlly": 0, "initialBuffCount": 0, "initialCrabCount": 0, "jungleCsBefore10Minutes": 0, "junglerTakedownsNearDamagedEpicMonster": 0, "kTurretsDestroyedBeforePlatesFall": 0, "kda": 0.6666666666666666, "killAfterHiddenWithAlly": 0, "killParticipation": 0.3, "killedChampTookFullTeamDamageSurvived": 0, "killsNearEnemyTurret": 0, "killsOnOtherLanesEarlyJungleAsLaner": 1, "killsOnRecentlyHealedByAramPack": 0, "killsUnderOwnTurret": 0, "killsWithHelpFromEpicMonster": 0, "knockEnemyIntoTeamAndKill": 0, "landSkillShotsEarlyGame": 1, "laneMinionsFirst10Minutes": 72, "laningPhaseGoldExpAdvantage": 0, "legendaryCount": 0, "lostAnInhibitor": 0, "maxCsAdvantageOnLaneOpponent": 51.75, "maxKillDeficit": 0, "maxLevelLeadLaneOpponent": 1, "moreEnemyJungleThanOpponent": 0, "multiKillOneSpell": 0, "multiTurretRiftHeraldCount": 0, "multikills": 0, "multikillsAfterAggressiveFlash": 0, "mythicItemUsed": 6672, "outerTurretExecutesBefore10Minutes": 0, "outnumberedKills": 0, "outnumberedNexusKill": 0, "perfectDragonSoulsTaken": 0, "perfectGame": 0, "pickKillWithAlly": 5, "playedChampSelectPosition": 1, "poroExplosions": 0, "quickCleanse": 0, "quickFirstTurret": 0, "quickSoloKills": 0, "riftHeraldTakedowns": 0, "saveAllyFromDeath": 0, "scuttleCrabKills": 1, "skillshotsDodged": 43, "skillshotsHit": 10, "snowballsHit": 0, "soloBaronKills": 0, "soloKills": 0, "stealthWardsPlaced": 6, "survivedSingleDigitHpCount": 0, "survivedThreeImmobilizesInFight": 6, "takedownOnFirstTurret": 0, "takedowns": 6, "takedownsAfterGainingLevelAdvantage": 0, "takedownsBeforeJungleMinionSpawn": 0, "takedownsFirstXMinutes": 3, "takedownsInAlcove": 0, "takedownsInEnemyFountain": 0, "teamBaronKills": 0, "teamDamagePercentage": 0.22449634750745623, "teamElderDragonKills": 0, "teamRiftHeraldKills": 2, "threeWardsOneSweeperCount": 0, "tookLargeDamageSurvived": 0, "turretPlatesTaken": 4, "turretTakedowns": 2, "turretsTakenWithRiftHerald": 0, "twentyMinionsIn3SecondsCount": 8, "unseenRecalls": 0, "visionScoreAdvantageLaneOpponent": -0.10222852230072021, "visionScorePerMinute": 0.6622342203888958, "wardTakedowns": 2, "wardTakedownsBefore20M": 0, "wardsGuarded": 0}, "champExperience": 9519, "champLevel": 12, "championId": 145, "championName": "Kaisa", "championTransform": 0, "commandPings": 15, "consumablesPurchased": 3, "damageDealtToBuildings": 4507, "damageDealtToObjectives": 22925, "damageDealtToTurrets": 4507, "damageSelfMitigated": 10656, "dangerPings": 0, "deaths": 9, "detectorWardsPlaced": 0, "doubleKills": 0, "dragonKills": 0, "eligibleForProgression": true, "enemyMissingPings": 3, "enemyVisionPings": 1, "firstBloodAssist": false, "firstBloodKill": false, "firstTowerAssist": false, "firstTowerKill": false, "gameEndedInEarlySurrender": false, "gameEndedInSurrender": false, "getBackPings": 7, "goldEarned": 10131, "goldSpent": 9350, "holdPings": 0, "individualPosition": "BOTTOM", "inhibitorKills": 0, "inhibitorTakedowns": 0, "inhibitorsLost": 2, "item0": 6672, "item1": 3006, "item2": 3153, "item3": 6677, "item4": 1018, "item5": 1042, "item6": 3340, "itemsPurchased": 21, "killingSprees": 0, "kills": 2, "lane": "BOTTOM", "largestCriticalStrike": 4452, "largestKillingSpree": 0, "largestMultiKill": 1, "longestTimeSpentLiving": 408, "magicDamageDealt": 20892, "magicDamageDealtToChampions": 6456, "magicDamageTaken": 10471, "needVisionPings": 0, "neutralMinionsKilled": 12, "nexusKills": 0, "nexusLost": 1, "nexusTakedowns": 0, "objectivesStolen": 0, "objectivesStolenAssists": 0, "onMyWayPings": 14, "participantId": 9, "pentaKills": 0, "perks": {"statPerks": {"defense": 5002, "flex": 5008, "offense": 5005}, "styles": [{"description": "primaryStyle", "selections": [{"perk": 9923, "var1": 56, "var2": 81, "var3": 0}, {"perk": 8139, "var1": 585, "var2": 0, "var3": 0}, {"perk": 8138, "var1": 7, "var2": 0, "var3": 0}, {"perk": 8135, "var1": 270, "var2": 3, "var3": 0}], "style": 8100}, {"description": "subStyle", "selections": [{"perk": 8304, "var1": 9, "var2": 4, "var3": 5}, {"perk": 8345, "var1": 3, "var2": 0, "var3": 0}], "style": 8300}]}, "physicalDamageDealt": 109479, "physicalDamageDealtToChampions": 11496, "physicalDamageTaken": 8439, "profileIcon": 2074, "pushPings": 0, "puuid": "jFlqFX1_gINeXgK5BSxlJFNm-naSe0GvSs9uKZ_VI-4SziZX-bsatn_GHwxaohopdq4kgW6mwLcvKQ", "quadraKills": 0, "riotIdName": "", "riotIdTagline": "", "role": "CARRY", "sightWardsBoughtInGame": 0, "spell1Casts": 68, "spell2Casts": 27, "spell3Casts": 45, "spell4Casts": 7, "summoner1Casts": 3, "summoner1Id": 4, "summoner2Casts": 4, "summoner2Id": 3, "summonerId": "0Ci52fcoiPmLoqivD6shkmlKTtvKRIhSIrFhHrHu9gtFXzKYY_N06Rq_dQ", "summonerLevel": 62, "summonerName": "Wh\u00f8 Wants a S\u00f8l\u00f8", "teamEarlySurrendered": false, "teamId": 200, "teamPosition": "BOTTOM", "timeCCingOthers": 3, "timePlayed": 1619, "totalDamageDealt": 146620, "totalDamageDealtToChampions": 19237, "totalDamageShieldedOnTeammates": 0, "totalDamageTaken": 20940, "totalHeal": 479, "totalHealsOnTeammates": 0, "totalMinionsKilled": 179, "totalTimeCCDealt": 31, "totalTimeSpentDead": 257, "totalUnitsHealed": 1, "tripleKills": 0, "trueDamageDealt": 16248, "trueDamageDealtToChampions": 1284, "trueDamageTaken": 2029, "turretKills": 1, "turretTakedowns": 2, "turretsLost": 10, "unrealKills": 0, "visionClearedPings": 0, "visionScore": 17, "visionWardsBoughtInGame": 0, "wardsKilled": 2, "wardsPlaced": 6, "win": false}, {"allInPings": 0, "assistMePings": 4, "assists": 7, "baitPings": 0, "baronKills": 0, "basicPings": 0, "bountyLevel": 0, "challenges": {"12AssistStreakCount": 0, "abilityUses": 167, "acesBefore15Minutes": 0, "alliedJungleMonsterKills": 0, "baronTakedowns": 0, "blastConeOppositeOpponentCount": 0, "bountyGold": 0, "buffsStolen": 0, "completeSupportQuestInTime": 1, "controlWardTimeCoverageInRiverOrEnemyHalf": 0.22130209442295087, "controlWardsPlaced": 5, "damagePerMinute": 288.93530538025374, "damageTakenOnTeamPercentage": 0.11606799586822827, "dancedWithRiftHerald": 0, "deathsByEnemyChamps": 6, "dodgeSkillShotsSmallWindow": 5, "doubleAces": 0, "dragonTakedowns": 1, "earliestDragonTakedown": 1103.791989635596, "earlyLaningPhaseGoldExpAdvantage": 0, "effectiveHealAndShielding": 5122.2978515625, "elderDragonKillsWithOpposingSoul": 0, "elderDragonMultikills": 0, "enemyChampionImmobilizations": 27, "enemyJungleMonsterKills": 0, "epicMonsterKillsNearEnemyJungler": 0, "epicMonsterKillsWithin30SecondsOfSpawn": 0, "epicMonsterSteals": 0, "epicMonsterStolenWithoutSmite": 0, "flawlessAces": 0, "fullTeamTakedown": 0, "gameLength": 1619.6166577078031, "getTakedownsInAllLanesEarlyJungleAsLaner": 0, "goldPerMinute": 254.06691988916154, "hadOpenNexus": 0, "highestWardKills": 1, "immobilizeAndKillWithAlly": 4, "initialBuffCount": 0, "initialCrabCount": 0, "jungleCsBefore10Minutes": 0, "junglerTakedownsNearDamagedEpicMonster": 0, "kTurretsDestroyedBeforePlatesFall": 0, "kda": 1.3333333333333333, "killAfterHiddenWithAlly": 0, "killParticipation": 0.4, "killedChampTookFullTeamDamageSurvived": 0, "killsNearEnemyTurret": 1, "killsOnOtherLanesEarlyJungleAsLaner": 0, "killsOnRecentlyHealedByAramPack": 0, "killsUnderOwnTurret": 0, "killsWithHelpFromEpicMonster": 0, "knockEnemyIntoTeamAndKill": 0, "landSkillShotsEarlyGame": 12, "laneMinionsFirst10Minutes": 1, "laningPhaseGoldExpAdvantage": 0, "legendaryCount": 0, "lostAnInhibitor": 0, "maxCsAdvantageOnLaneOpponent": 0, "maxKillDeficit": 0, "maxLevelLeadLaneOpponent": 1, "moreEnemyJungleThanOpponent": 0, "multiKillOneSpell": 0, "multiTurretRiftHeraldCount": 0, "multikills": 0, "multikillsAfterAggressiveFlash": 0, "mythicItemUsed": 4005, "outerTurretExecutesBefore10Minutes": 0, "outnumberedKills": 1, "outnumberedNexusKill": 0, "perfectDragonSoulsTaken": 0, "perfectGame": 0, "pickKillWithAlly": 7, "playedChampSelectPosition": 1, "poroExplosions": 0, "quickCleanse": 0, "quickFirstTurret": 0, "quickSoloKills": 0, "riftHeraldTakedowns": 0, "saveAllyFromDeath": 0, "scuttleCrabKills": 0, "skillshotsDodged": 29, "skillshotsHit": 50, "snowballsHit": 0, "soloBaronKills": 0, "soloKills": 0, "stealthWardsPlaced": 24, "survivedSingleDigitHpCount": 0, "survivedThreeImmobilizesInFight": 0, "takedownOnFirstTurret": 0, "takedowns": 8, "takedownsAfterGainingLevelAdvantage": 0, "takedownsBeforeJungleMinionSpawn": 0, "takedownsFirstXMinutes": 4, "takedownsInAlcove": 0, "takedownsInEnemyFountain": 0, "teamBaronKills": 0, "teamDamagePercentage": 0.09101593547223666, "teamElderDragonKills": 0, "teamRiftHeraldKills": 2, "threeWardsOneSweeperCount": 0, "tookLargeDamageSurvived": 0, "turretPlatesTaken": 2, "turretTakedowns": 1, "turretsTakenWithRiftHerald": 0, "twentyMinionsIn3SecondsCount": 0, "unseenRecalls": 0, "visionScoreAdvantageLaneOpponent": 0.4147012233734131, "visionScorePerMinute": 3.008920102141739, "wardTakedowns": 10, "wardTakedownsBefore20M": 6, "wardsGuarded": 0}, "champExperience": 8014, "champLevel": 11, "championId": 267, "championName": "Nami", "championTransform": 0, "commandPings": 9, "consumablesPurchased": 9, "damageDealtToBuildings": 1670, "damageDealtToObjectives": 2816, "damageDealtToTurrets": 1670, "damageSelfMitigated": 5233, "dangerPings": 0, "deaths": 6, "detectorWardsPlaced": 5, "doubleKills": 0, "dragonKills": 0, "eligibleForProgression": true, "enemyMissingPings": 8, "enemyVisionPings": 0, "firstBloodAssist": false, "firstBloodKill": false, "firstTowerAssist": false, "firstTowerKill": false, "gameEndedInEarlySurrender": false, "gameEndedInSurrender": false, "getBackPings": 10, "goldEarned": 6858, "goldSpent": 6750, "holdPings": 0, "individualPosition": "UTILITY", "inhibitorKills": 0, "inhibitorTakedowns": 0, "inhibitorsLost": 2, "item0": 3853, "item1": 3011, "item2": 0, "item3": 0, "item4": 3158, "item5": 4005, "item6": 3364, "itemsPurchased": 25, "killingSprees": 0, "kills": 1, "lane": "BOTTOM", "largestCriticalStrike": 0, "largestKillingSpree": 0, "largestMultiKill": 1, "longestTimeSpentLiving": 508, "magicDamageDealt": 12482, "magicDamageDealtToChampions": 6798, "magicDamageTaken": 7005, "needVisionPings": 0, "neutralMinionsKilled": 0, "nexusKills": 0, "nexusLost": 1, "nexusTakedowns": 0, "objectivesStolen": 0, "objectivesStolenAssists": 0, "onMyWayPings": 3, "participantId": 10, "pentaKills": 0, "perks": {"statPerks": {"defense": 5002, "flex": 5003, "offense": 5008}, "styles": [{"description": "primaryStyle", "selections": [{"perk": 8214, "var1": 425, "var2": 1398, "var3": 0}, {"perk": 8226, "var1": 250, "var2": 285, "var3": 0}, {"perk": 8210, "var1": 0, "var2": 0, "var3": 0}, {"perk": 8236, "var1": 24, "var2": 0, "var3": 0}], "style": 8200}, {"description": "subStyle", "selections": [{"perk": 8473, "var1": 365, "var2": 0, "var3": 0}, {"perk": 8453, "var1": 554, "var2": 263, "var3": 0}], "style": 8400}]}, "physicalDamageDealt": 2523, "physicalDamageDealtToChampions": 595, "physicalDamageTaken": 4589, "profileIcon": 3163, "pushPings": 0, "puuid": "yGux9w-P3Ue5zCobrjqusGcAbwxmtD5CyC8bL5rL1H5dTnN4VEbhQazFPg2PZO77vZ2XzC26WmVdkg", "quadraKills": 0, "riotIdName": "", "riotIdTagline": "", "role": "SUPPORT", "sightWardsBoughtInGame": 0, "spell1Casts": 38, "spell2Casts": 45, "spell3Casts": 75, "spell4Casts": 9, "summoner1Casts": 4, "summoner1Id": 4, "summoner2Casts": 6, "summoner2Id": 14, "summonerId": "2nuiiBy1ZbXiHCgSdaaxCeslQyVd4sS3q5xGWx2W-oObyNU", "summonerLevel": 369, "summonerName": "ByF\u00e1r S\u00e1nyed", "teamEarlySurrendered": false, "teamId": 200, "teamPosition": "UTILITY", "timeCCingOthers": 36, "timePlayed": 1619, "totalDamageDealt": 16982, "totalDamageDealtToChampions": 7799, "totalDamageShieldedOnTeammates": 1455, "totalDamageTaken": 12649, "totalHeal": 5915, "totalHealsOnTeammates": 3666, "totalMinionsKilled": 12, "totalTimeCCDealt": 177, "totalTimeSpentDead": 136, "totalUnitsHealed": 3, "tripleKills": 0, "trueDamageDealt": 1976, "trueDamageDealtToChampions": 406, "trueDamageTaken": 1055, "turretKills": 1, "turretTakedowns": 1, "turretsLost": 10, "unrealKills": 0, "visionClearedPings": 0, "visionScore": 81, "visionWardsBoughtInGame": 6, "wardsKilled": 10, "wardsPlaced": 29, "win": false}], "platformId": "EUN1", "queueId": 420, "teams": [{"bans": [{"championId": 875, "pickTurn": 1}, {"championId": 57, "pickTurn": 2}, {"championId": 74, "pickTurn": 3}, {"championId": 111, "pickTurn": 4}, {"championId": 154, "pickTurn": 5}], "objectives": {"baron": {"first": true, "kills": 1}, "champion": {"first": true, "kills": 31}, "dragon": {"first": true, "kills": 3}, "inhibitor": {"first": true, "kills": 2}, "riftHerald": {"first": false, "kills": 1}, "tower": {"first": true, "kills": 10}}, "teamId": 100, "win": true}, {"bans": [{"championId": 38, "pickTurn": 6}, {"championId": 39, "pickTurn": 7}, {"championId": 51, "pickTurn": 8}, {"championId": 77, "pickTurn": 9}, {"championId": 19, "pickTurn": 10}], "objectives": {"baron": {"first": false, "kills": 0}, "champion": {"first": false, "kills": 20}, "dragon": {"first": false, "kills": 1}, "inhibitor": {"first": false, "kills": 0}, "riftHerald": {"first": true, "kills": 1}, "tower": {"first": false, "kills": 5}}, "teamId": 200, "win": false}], "tournamentCode": ""}}